AUTHORS.rst
CONTRIBUTING.rst
HISTORY.rst
LICENSE
MANIFEST.in
README.rst
VERSION.rst
setup.cfg
setup.py
docs/Makefile
docs/authors.rst
docs/conf.py
docs/contributing.rst
docs/history.rst
docs/index.rst
docs/installation.rst
docs/make.bat
docs/readme.rst
docs/usage.rst
godaddycli/__init__.py
godaddycli/godaddycli.py
godaddycli.egg-info/PKG-INFO
godaddycli.egg-info/SOURCES.txt
godaddycli.egg-info/dependency_links.txt
godaddycli.egg-info/entry_points.txt
godaddycli.egg-info/not-zip-safe
godaddycli.egg-info/pbr.json
godaddycli.egg-info/requires.txt
godaddycli.egg-info/top_level.txt
tests/__init__.py
tests/test_godaddycli.py