Metadata-Version: 1.1
Name: godaddycli
Version: 0.1.4
Summary: Command Line Interface to GoDaddy.com based on PyGoDaddy Library
Home-page: https://github.com/wkoszek/godaddycli
Author: Wojciech A. Koszek
Author-email: wojciech@koszek.com
License: BSD
Keywords: godaddycli
Platform: UNKNOWN
Classifier: Development Status :: 2 - Pre-Alpha
Classifier: Intended Audience :: Developers
Classifier: License :: OSI Approved :: BSD License
Classifier: Natural Language :: English
Classifier: Programming Language :: Python :: 2
Classifier: Programming Language :: Python :: 2.6
Classifier: Programming Language :: Python :: 2.7
Classifier: Programming Language :: Python :: 3
Classifier: Programming Language :: Python :: 3.3
Classifier: Programming Language :: Python :: 3.4
